mcp_server_time/__init__.py
mcp_server_time/__main__.py
mcp_server_time/server.py
time_mcp_server-0.1.0.dist-info/METADATA
time_mcp_server-0.1.0.dist-info/WHEEL
time_mcp_server-0.1.0.dist-info/entry_points.txt
time_mcp_server-0.1.0.dist-info/top_level.txt
time_mcp_server-0.1.0.dist-info/RECORD
