Metadata-Version: 2.4
Name: time-mcp-server
Version: 0.1.0
Summary: A Model Context Protocol server providing tools for time queries and timezone conversions for LLMs
Author-email: Mariusz 'maledorak' Korzekwa <mariusz@korzekwa.dev>
License: MIT
Keywords: time,timezone,mcp,llm
Classifier: Development Status :: 4 - Beta
Classifier: Intended Audience :: Developers
Classifier: License :: OSI Approved :: MIT License
Classifier: Programming Language :: Python :: 3
Classifier: Programming Language :: Python :: 3.10
Requires-Python: >=3.13
Requires-Dist: argparse>=1.4.0
Requires-Dist: asyncio>=3.4.3
Requires-Dist: freezegun>=1.5.1
Requires-Dist: mcp>=1.5.0
Requires-Dist: pydantic>=2.10.6
Requires-Dist: pyright>=1.1.398
Requires-Dist: pytest>=8.3.5
Requires-Dist: ruff>=0.11.2
Requires-Dist: tzdata>=2025.2
